iode_gui/__init__.py
iode_gui/abstract_main_window.py
iode_gui/color_theme.py
iode_gui/iode_resource_rc.py
iode_gui/main.py
iode_gui/main_window.py
iode_gui/settings.py
iode_gui/super.py
iode_gui/ui_main_window.py
iode_gui/utils.py
iode_gui/doc/keyboard_shortcuts.pdf
iode_gui/iode_objs/__init__.py
iode_gui/iode_objs/delegates/__init__.py
iode_gui/iode_objs/delegates/base_delegate.py
iode_gui/iode_objs/delegates/comments_delegate.py
iode_gui/iode_objs/delegates/equations_delegate.py
iode_gui/iode_objs/delegates/identities_delegate.py
iode_gui/iode_objs/delegates/lists_delegate.py
iode_gui/iode_objs/delegates/scalars_delegate.py
iode_gui/iode_objs/delegates/tables_delegate.py
iode_gui/iode_objs/delegates/variables_delegate.py
iode_gui/iode_objs/edit/__init__.py
iode_gui/iode_objs/edit/edit_equation.py
iode_gui/iode_objs/edit/edit_iode_obj.py
iode_gui/iode_objs/edit/edit_table.py
iode_gui/iode_objs/edit/edit_table_delegate.py
iode_gui/iode_objs/edit/edit_table_model.py
iode_gui/iode_objs/edit/edit_table_view.py
iode_gui/iode_objs/edit/edit_vars_sample.py
iode_gui/iode_objs/edit/ui_edit_equation.py
iode_gui/iode_objs/edit/ui_edit_iode_obj.py
iode_gui/iode_objs/edit/ui_edit_table.py
iode_gui/iode_objs/edit/ui_edit_vars_sample.py
iode_gui/iode_objs/estimation/__init__.py
iode_gui/iode_objs/estimation/correlation_matrix_model.py
iode_gui/iode_objs/estimation/estimation_coefs.py
iode_gui/iode_objs/estimation/estimation_results.py
iode_gui/iode_objs/estimation/tests_eqs_model.py
iode_gui/iode_objs/estimation/ui_estimation_coefs.py
iode_gui/iode_objs/estimation/ui_estimation_results.py
iode_gui/iode_objs/misc/__init__.py
iode_gui/iode_objs/misc/dyn_adjustment.py
iode_gui/iode_objs/misc/ui_dyn_adjustment.py
iode_gui/iode_objs/misc/ui_unit_root.py
iode_gui/iode_objs/misc/unit_root.py
iode_gui/iode_objs/models/__init__.py
iode_gui/iode_objs/models/abstract_table_model.py
iode_gui/iode_objs/models/computed_table_model.py
iode_gui/iode_objs/models/numerical_table_model.py
iode_gui-7.0.4.dist-info/licenses/LICENSE.md
iode_gui-7.0.4.dist-info/METADATA
iode_gui-7.0.4.dist-info/WHEEL
iode_gui-7.0.4.dist-info/entry_points.txt
iode_gui-7.0.4.dist-info/top_level.txt
iode_gui-7.0.4.dist-info/RECORD
