Metadata-Version: 2.4
Name: iode-gui
Version: 7.0.4
Summary: Graphical User Interface (GUI) for the iode python package
Author-email: Alix Damman <ald@plan.be>, Yannick Van den Abbeel <yvda@plan.be>, Jean-Marc Paul <jmarc.paul@gmail.com>, Geert Bryon <gb@plan.be>
License-Expression: GPL-3.0-or-later
Project-URL: Homepage, https://iode.readthedocs.io/en/stable/
Classifier: Development Status :: 4 - Beta
Classifier: Operating System :: Microsoft :: Windows
Classifier: Intended Audience :: Science/Research
Classifier: Intended Audience :: Developers
Classifier: Programming Language :: Python
Classifier: Programming Language :: Python :: 3
Classifier: Programming Language :: Python :: 3.10
Classifier: Programming Language :: Python :: 3.11
Classifier: Programming Language :: Python :: 3.12
Classifier: Topic :: Scientific/Engineering
Classifier: Topic :: Software Development :: Libraries
Requires-Python: >=3.10
License-File: LICENSE.md
Requires-Dist: numpy
Requires-Dist: pandas
Requires-Dist: matplotlib
Requires-Dist: iode
Requires-Dist: pyside6>=6.5
Requires-Dist: qtconsole
Requires-Dist: ipython
Dynamic: license-file
